occe-api/__init__.py
occe-api/api.py
occe_api/__init__.py
occe_api/main.py
occe_api-1.0.1.dist-info/LICENSE
occe_api-1.0.1.dist-info/METADATA
occe_api-1.0.1.dist-info/WHEEL
occe_api-1.0.1.dist-info/top_level.txt
occe_api-1.0.1.dist-info/RECORD
