Metadata-Version: 2.1
Name: occe-api
Version: 1.0.1
Summary: Python wrapper for occe.io stock
Home-page: http://occe.io/
Author: surugh
Author-email: surugh@gmail.com
Project-URL: Documentation, http://occe.io/info#api
Keywords: occe python
Classifier: Programming Language :: Python :: 3.11
Classifier: License :: OSI Approved :: MIT License
Classifier: Operating System :: OS Independent
Requires-Python: >=3.10
License-File: LICENSE
Requires-Dist: requests (>=2.28.2)
